{
  "$schema": "https://vega.github.io/schema/vega-lite/v2.6.0.json",
  "config": {
    "view": {
      "height": 300,
      "width": 400
    }
  },
  "data": {
    "name": "data-befba9a85dc339b9acaf9ca72544468e"
  },
  "datasets": {
    "data-befba9a85dc339b9acaf9ca72544468e": [
      {
        "y": 0.0
      },
      {
        "y": 0.0003982600187315486
      },
      {
        "y": 0.0007965200374630972
      },
      {
        "y": 0.0011947800561946458
      },
      {
        "y": 0.0015930400749261944
      },
      {
        "y": 0.001991300093657743
      },
      {
        "y": 0.0023895601123892917
      },
      {
        "y": 0.00278782013112084
      },
      {
        "y": 0.0031860801498523887
      },
      {
        "y": 0.0035843401685839373
      },
      {
        "y": 0.003982600187315486
      },
      {
        "y": 0.004380860206047035
      },
      {
        "y": 0.004779120224778583
      },
      {
        "y": 0.005177380243510132
      },
      {
        "y": 0.00557564026224168
      },
      {
        "y": 0.005973900280973229
      },
      {
        "y": 0.0063721602997047775
      },
      {
        "y": 0.006770420318436326
      },
      {
        "y": 0.0071686803371678745
      },
      {
        "y": 0.007566940355899423
      },
      {
        "y": 0.007965200374630972
      },
      {
        "y": 0.008363460393362521
      },
      {
        "y": 0.00876172041209407
      },
      {
        "y": 0.009159980430825618
      },
      {
        "y": 0.009558240449557167
      },
      {
        "y": 0.009956500468288715
      },
      {
        "y": 0.010354760487020264
      },
      {
        "y": 0.010753020505751812
      },
      {
        "y": 0.01115128052448336
      },
      {
        "y": 0.01154954054321491
      },
      {
        "y": 0.011947800561946458
      },
      {
        "y": 0.012346060580678006
      },
      {
        "y": 0.012744320599409555
      },
      {
        "y": 0.013142580618141103
      },
      {
        "y": 0.013540840636872652
      },
      {
        "y": 0.0139391006556042
      },
      {
        "y": 0.014337360674335749
      },
      {
        "y": 0.014735620693067298
      },
      {
        "y": 0.015133880711798846
      },
      {
        "y": 0.015532140730530395
      },
      {
        "y": 0.015930400749261945
      },
      {
        "y": 0.016328660767993494
      },
      {
        "y": 0.016726920786725042
      },
      {
        "y": 0.01712518080545659
      },
      {
        "y": 0.01752344082418814
      },
      {
        "y": 0.017921700842919688
      },
      {
        "y": 0.018319960861651236
      },
      {
        "y": 0.018718220880382785
      },
      {
        "y": 0.019116480899114333
      },
      {
        "y": 0.019514740917845882
      }
    ]
  },
  "encoding": {
    "x": {
      "value": 70.0
    },
    "y": {
      "field": "y",
      "title": null,
      "type": "quantitative"
    }
  },
  "mark": {
    "color": "#B71ECF",
    "type": "line"
  }
}